{
  "chat_lieu": [
    {
      "id": 1,
      "ten_chat_lieu": "Dạ (Wool)",
      "trang_thai": "Hoạt động"
    },
    {
      "id": 2,
      "ten_chat_lieu": "Nỉ (Fleece)",
      "trang_thai": "Hoạt động"
    },
    {
      "id": 3,
      "ten_chat_lieu": "Kaki (Khaki)",
      "trang_thai": "Hoạt động"
    },
    {
      "id": 4,
      "ten_chat_lieu": "Polyester",
      "trang_thai": "Hoạt động"
    },
    {
      "id": 5,
      "ten_chat_lieu": "Cotton Cao Cấp",
      "trang_thai": "Hoạt động"
    }
  ],
  "thuong_hieu": [
    {
      "id": 1,
      "ten_thuong_hieu": "FamiCoats",
      "logo": "logo_famicoats.png",
      "quoc_gia": "Việt Nam",
      "mo_ta": "Thương hiệu áo khoác cao cấp dành cho gia đình.",
      "trang_thai": "Hoạt động"
    },
    {
      "id": 2,
      "ten_thuong_hieu": "Zara",
      "logo": "logo_zara.png",
      "quoc_gia": "Tây Ban Nha",
      "mo_ta": "Thương hiệu thời trang nhanh quốc tế nổi tiếng.",
      "trang_thai": "Hoạt động"
    },
    {
      "id": 3,
      "ten_thuong_hieu": "Uniqlo",
      "logo": "logo_uniqlo.png",
      "quoc_gia": "Nhật Bản",
      "mo_ta": "Thời trang tối giản, tiện dụng công nghệ LifeWear.",
      "trang_thai": "Hoạt động"
    },
    {
      "id": 4,
      "ten_thuong_hieu": "H&M",
      "logo": "logo_hm.png",
      "quoc_gia": "Thụy Điển",
      "mo_ta": "Thời trang xu hướng, phong cách hiện đại trẻ trung.",
      "trang_thai": "Hoạt động"
    }
  ],
  "danh_muc": [
    {
      "id": 1,
      "ten_danh_muc": "Áo Măng Tô (Trench Coat)",
      "mo_ta": "Áo khoác dáng dài thanh lịch giữ ấm tốt.",
      "trang_thai": "Hoạt động"
    },
    {
      "id": 2,
      "ten_danh_muc": "Áo Phao (Down Jacket)",
      "mo_ta": "Áo khoác phao dày dặn giữ nhiệt siêu tốt.",
      "trang_thai": "Hoạt động"
    },
    {
      "id": 3,
      "ten_danh_muc": "Áo Gió (Windbreaker)",
      "mo_ta": "Áo khoác mỏng nhẹ chống gió bụi và cản nước.",
      "trang_thai": "Hoạt động"
    },
    {
      "id": 4,
      "ten_danh_muc": "Áo Dạ (Wool Coat)",
      "mo_ta": "Áo khoác dạ ấm áp sang trọng lịch lãm.",
      "trang_thai": "Hoạt động"
    },
    {
      "id": 5,
      "ten_danh_muc": "Áo Blazer",
      "mo_ta": "Áo khoác phong cách Smart Casual thanh lịch.",
      "trang_thai": "Hoạt động"
    }
  ],
  "kich_thuoc": [
    {
      "id": 1,
      "ten_kich_thuoc": "S",
      "mo_ta": "Kích cỡ nhỏ",
      "trang_thai": "Hoạt động"
    },
    {
      "id": 2,
      "ten_kich_thuoc": "M",
      "mo_ta": "Kích cỡ trung bình",
      "trang_thai": "Hoạt động"
    },
    {
      "id": 3,
      "ten_kich_thuoc": "L",
      "mo_ta": "Kích cỡ lớn",
      "trang_thai": "Hoạt động"
    },
    {
      "id": 4,
      "ten_kich_thuoc": "XL",
      "mo_ta": "Kích cỡ cực lớn",
      "trang_thai": "Hoạt động"
    },
    {
      "id": 5,
      "ten_kich_thuoc": "XXL",
      "mo_ta": "Kích cỡ ngoại cỡ",
      "trang_thai": "Hoạt động"
    }
  ],
  "mau_sac": [
    {
      "id": 1,
      "ten_mau": "Đen",
      "ma_mau_hex": "#000000",
      "trang_thai": "Hoạt động"
    },
    {
      "id": 2,
      "ten_mau": "Trắng",
      "ma_mau_hex": "#FFFFFF",
      "trang_thai": "Hoạt động"
    },
    {
      "id": 3,
      "ten_mau": "Đỏ đô",
      "ma_mau_hex": "#800020",
      "trang_thai": "Hoạt động"
    },
    {
      "id": 4,
      "ten_mau": "Xanh navy",
      "ma_mau_hex": "#000080",
      "trang_thai": "Hoạt động"
    },
    {
      "id": 5,
      "ten_mau": "Be (Beige)",
      "ma_mau_hex": "#F5F5DC",
      "trang_thai": "Hoạt động"
    }
  ],
  "kieu_dang": [
    {
      "id": 1,
      "ten_kieu_dang": "Slim-fit",
      "trang_thai": "Hoạt động"
    },
    {
      "id": 2,
      "ten_kieu_dang": "Regular-fit",
      "trang_thai": "Hoạt động"
    },
    {
      "id": 3,
      "ten_kieu_dang": "Oversize",
      "trang_thai": "Hoạt động"
    },
    {
      "id": 4,
      "ten_kieu_dang": "Loose-fit",
      "trang_thai": "Hoạt động"
    }
  ],
  "san_pham": [
    {
      "id": "SP001",
      "id_danh_muc": 4,
      "id_thuong_hieu": 1,
      "id_chat_lieu": 1,
      "ten_san_pham": "Áo Khoác Dạ Dáng Dài Fami Luxury",
      "mo_ta": "Áo khoác dạ dáng dài thiết kế sang trọng, chất liệu dạ cừu tự nhiên giữ ấm cực tốt.",
      "doi_tuong": "Nữ",
      "xuat_xu": "Việt Nam",
      "thuong_hieu_noi_bo": true,
      "bao_hanh": "12 tháng",
      "huong_dan_bao_quan": "Giặt khô, không vắt máy, ủi hơi nước ở nhiệt độ thấp.",
      "tinh_nang": "Giữ ấm tốt, chống nhăn, tôn dáng.",
      "trang_thai": "Kinh doanh"
    },
    {
      "id": "SP002",
      "id_danh_muc": 2,
      "id_thuong_hieu": 1,
      "id_chat_lieu": 4,
      "ten_san_pham": "Áo Phao Béo Siêu Nhẹ Fami Warm",
      "mo_ta": "Áo phao lót bông siêu nhẹ, cản gió tốt, thích hợp cho thời tiết rét đậm rét hại.",
      "doi_tuong": "Unisex",
      "xuat_xu": "Việt Nam",
      "thuong_hieu_noi_bo": true,
      "bao_hanh": "6 tháng",
      "huong_dan_bao_quan": "Giặt tay hoặc giặt máy chế độ nhẹ, không dùng chất tẩy mạnh.",
      "tinh_nang": "Chống thấm nước nhẹ, cản gió, cực kỳ ấm áp.",
      "trang_thai": "Kinh doanh"
    },
    {
      "id": "SP003",
      "id_danh_muc": 1,
      "id_thuong_hieu": 2,
      "id_chat_lieu": 3,
      "ten_san_pham": "Áo Trench Coat Zara Classic",
      "mo_ta": "Áo măng tô dáng dài phong cách cổ điển Tây Âu, tôn lên vẻ thanh lịch thời thượng.",
      "doi_tuong": "Nam",
      "xuat_xu": "Tây Ban Nha",
      "thuong_hieu_noi_bo": false,
      "bao_hanh": "Không bảo hành",
      "huong_dan_bao_quan": "Giặt tay hoặc giặt khô, tránh ánh nắng trực tiếp khi phơi.",
      "tinh_nang": "Thời trang, cản gió nhẹ.",
      "trang_thai": "Kinh doanh"
    },
    {
      "id": "SP004",
      "id_danh_muc": 3,
      "id_thuong_hieu": 3,
      "id_chat_lieu": 4,
      "ten_san_pham": "Áo Gió Chống Nước Uniqlo Blocktech",
      "mo_ta": "Áo gió công nghệ Blocktech chống thấm nước tuyệt đối, cản gió tối ưu, thích hợp đi mưa nhẹ.",
      "doi_tuong": "Unisex",
      "xuat_xu": "Nhật Bản",
      "thuong_hieu_noi_bo": false,
      "bao_hanh": "Không bảo hành",
      "huong_dan_bao_quan": "Giặt máy nước lạnh, không sấy nhiệt độ cao.",
      "tinh_nang": "Chống nước tuyệt đối, chống tia UV, mỏng nhẹ.",
      "trang_thai": "Kinh doanh"
    },
    {
      "id": "SP005",
      "id_danh_muc": 5,
      "id_thuong_hieu": 1,
      "id_chat_lieu": 5,
      "ten_san_pham": "Áo Blazer Cotton Fami Smart Casual",
      "mo_ta": "Áo khoác blazer mỏng nhẹ phong cách Hàn Quốc, thích hợp đi làm hoặc đi chơi.",
      "doi_tuong": "Nam",
      "xuat_xu": "Việt Nam",
      "thuong_hieu_noi_bo": true,
      "bao_hanh": "3 tháng",
      "huong_dan_bao_quan": "Giặt tay nước lạnh, ủi ở nhiệt độ trung bình.",
      "tinh_nang": "Thoáng khí, mềm mại, co giãn nhẹ.",
      "trang_thai": "Kinh doanh"
    }
  ],
  "hinh_anh_san_pham": [
    {
      "id": 1,
      "id_chi_tiet_san_pham": 1,
      "duong_dan": "anh1.png",
      "la_anh_chinh": true,
      "thu_tu": 1
    },
    {
      "id": 2,
      "id_chi_tiet_san_pham": 1,
      "duong_dan": "anh2.png",
      "la_anh_chinh": false,
      "thu_tu": 2
    },
    {
      "id": 3,
      "id_chi_tiet_san_pham": 2,
      "duong_dan": "anh3.png",
      "la_anh_chinh": true,
      "thu_tu": 1
    },
    {
      "id": 4,
      "id_chi_tiet_san_pham": 3,
      "duong_dan": "anh4.png",
      "la_anh_chinh": true,
      "thu_tu": 1
    },
    {
      "id": 5,
      "id_chi_tiet_san_pham": 4,
      "duong_dan": "anh5.png",
      "la_anh_chinh": true,
      "thu_tu": 1
    },
    {
      "id": 6,
      "id_chi_tiet_san_pham": 5,
      "duong_dan": "anh6.png",
      "la_anh_chinh": true,
      "thu_tu": 1
    },
    {
      "id": 7,
      "id_chi_tiet_san_pham": 6,
      "duong_dan": "anh7.png",
      "la_anh_chinh": true,
      "thu_tu": 1
    },
    {
      "id": 8,
      "id_chi_tiet_san_pham": 7,
      "duong_dan": "anh8.png",
      "la_anh_chinh": true,
      "thu_tu": 1
    },
    {
      "id": 9,
      "id_chi_tiet_san_pham": 8,
      "duong_dan": "anh9.png",
      "la_anh_chinh": true,
      "thu_tu": 1
    },
    {
      "id": 10,
      "id_chi_tiet_san_pham": 9,
      "duong_dan": "anh10.png",
      "la_anh_chinh": true,
      "thu_tu": 1
    }
  ],
  "chi_tiet_san_pham": [
    {
      "id": 1,
      "id_san_pham": "SP001",
      "id_kich_thuoc": 2,
      "id_mau_sac": 1,
      "id_kieu_dang": 1,
      "gia_nhap": 500000.0,
      "gia_ban": 950000.0,
      "gia_khuyen_mai": 850000.0,
      "so_luong_ton": 50,
      "trong_luong": 0.8,
      "chieau_dai": 95.0,
      "chieu_rong": 48.0,
      "do_day": 2.5,
      "chong_nuoc": false,
      "chong_gio": true,
      "giu_nhiet": true,
      "trang_thai": "Hoạt động"
    },
    {
      "id": 2,
      "id_san_pham": "SP001",
      "id_kich_thuoc": 3,
      "id_mau_sac": 5,
      "id_kieu_dang": 1,
      "gia_nhap": 500000.0,
      "gia_ban": 950000.0,
      "gia_khuyen_mai": 850000.0,
      "so_luong_ton": 30,
      "trong_luong": 0.85,
      "chieau_dai": 98.0,
      "chieu_rong": 50.0,
      "do_day": 2.5,
      "chong_nuoc": false,
      "chong_gio": true,
      "giu_nhiet": true,
      "trang_thai": "Hoạt động"
    },
    {
      "id": 3,
      "id_san_pham": "SP002",
      "id_kich_thuoc": 3,
      "id_mau_sac": 4,
      "id_kieu_dang": 3,
      "gia_nhap": 400000.0,
      "gia_ban": 799000.0,
      "gia_khuyen_mai": 699000.0,
      "so_luong_ton": 100,
      "trong_luong": 1.1,
      "chieau_dai": 75.0,
      "chieu_rong": 60.0,
      "do_day": 5.0,
      "chong_nuoc": true,
      "chong_gio": true,
      "giu_nhiet": true,
      "trang_thai": "Hoạt động"
    },
    {
      "id": 4,
      "id_san_pham": "SP002",
      "id_kich_thuoc": 4,
      "id_mau_sac": 1,
      "id_kieu_dang": 3,
      "gia_nhap": 400000.0,
      "gia_ban": 799000.0,
      "gia_khuyen_mai": 749000.0,
      "so_luong_ton": 40,
      "trong_luong": 1.2,
      "chieau_dai": 78.0,
      "chieu_rong": 62.0,
      "do_day": 5.0,
      "chong_nuoc": true,
      "chong_gio": true,
      "giu_nhiet": true,
      "trang_thai": "Hoạt động"
    },
    {
      "id": 5,
      "id_san_pham": "SP003",
      "id_kich_thuoc": 2,
      "id_mau_sac": 1,
      "id_kieu_dang": 2,
      "gia_nhap": 600000.0,
      "gia_ban": 1200000.0,
      "gia_khuyen_mai": 1050000.0,
      "so_luong_ton": 20,
      "trong_luong": 0.9,
      "chieau_dai": 100.0,
      "chieu_rong": 52.0,
      "do_day": 1.8,
      "chong_nuoc": false,
      "chong_gio": true,
      "giu_nhiet": false,
      "trang_thai": "Hoạt động"
    },
    {
      "id": 6,
      "id_san_pham": "SP003",
      "id_kich_thuoc": 3,
      "id_mau_sac": 4,
      "id_kieu_dang": 2,
      "gia_nhap": 600000.0,
      "gia_ban": 1200000.0,
      "gia_khuyen_mai": null,
      "so_luong_ton": 15,
      "trong_luong": 0.95,
      "chieau_dai": 103.0,
      "chieu_rong": 54.0,
      "do_day": 1.8,
      "chong_nuoc": false,
      "chong_gio": true,
      "giu_nhiet": false,
      "trang_thai": "Hoạt động"
    },
    {
      "id": 7,
      "id_san_pham": "SP004",
      "id_kich_thuoc": 1,
      "id_mau_sac": 3,
      "id_kieu_dang": 2,
      "gia_nhap": 250000.0,
      "gia_ban": 499000.0,
      "gia_khuyen_mai": null,
      "so_luong_ton": 60,
      "trong_luong": 0.3,
      "chieau_dai": 65.0,
      "chieu_rong": 45.0,
      "do_day": 0.8,
      "chong_nuoc": true,
      "chong_gio": true,
      "giu_nhiet": false,
      "trang_thai": "Hoạt động"
    },
    {
      "id": 8,
      "id_san_pham": "SP004",
      "id_kich_thuoc": 2,
      "id_mau_sac": 4,
      "id_kieu_dang": 2,
      "gia_nhap": 250000.0,
      "gia_ban": 499000.0,
      "gia_khuyen_mai": 449000.0,
      "so_luong_ton": 80,
      "trong_luong": 0.32,
      "chieau_dai": 68.0,
      "chieu_rong": 47.0,
      "do_day": 0.8,
      "chong_nuoc": true,
      "chong_gio": true,
      "giu_nhiet": false,
      "trang_thai": "Hoạt động"
    },
    {
      "id": 9,
      "id_san_pham": "SP005",
      "id_kich_thuoc": 2,
      "id_mau_sac": 1,
      "id_kieu_dang": 2,
      "gia_nhap": 300000.0,
      "gia_ban": 599000.0,
      "gia_khuyen_mai": null,
      "so_luong_ton": 35,
      "trong_luong": 0.6,
      "chieau_dai": 72.0,
      "chieu_rong": 50.0,
      "do_day": 1.2,
      "chong_nuoc": false,
      "chong_gio": false,
      "giu_nhiet": false,
      "trang_thai": "Hoạt động"
    },
    {
      "id": 10,
      "id_san_pham": "SP005",
      "id_kich_thuoc": 3,
      "id_mau_sac": 5,
      "id_kieu_dang": 2,
      "gia_nhap": 300000.0,
      "gia_ban": 599000.0,
      "gia_khuyen_mai": 529000.0,
      "so_luong_ton": 25,
      "trong_luong": 0.63,
      "chieau_dai": 74.0,
      "chieu_rong": 52.0,
      "do_day": 1.2,
      "chong_nuoc": false,
      "chong_gio": false,
      "giu_nhiet": false,
      "trang_thai": "Hoạt động"
    }
  ]
}
